exceptions.py
object.py
smartcrawler.py
smartcrawler-0.0.3.dist-info/LICENCE
smartcrawler-0.0.3.dist-info/METADATA
smartcrawler-0.0.3.dist-info/WHEEL
smartcrawler-0.0.3.dist-info/top_level.txt
smartcrawler-0.0.3.dist-info/RECORD
